Metadata-Version: 1.0
Name: ljd-distributions
Version: 0.1
Summary: Gaussian and Binomial distributions
Home-page: UNKNOWN
Author: Lucky Jeagun Daniel
Author-email: luckyjeagun1@gmail.com
License: UNKNOWN
Platform: UNKNOWN
